nkunyim_iam/__init__.py
nkunyim_iam/admin.py
nkunyim_iam/apps.py
nkunyim_iam/authentication.py
nkunyim_iam/commands.py
nkunyim_iam/middleware.py
nkunyim_iam/models.py
nkunyim_iam/auth/__init__.py
nkunyim_iam/auth/consts.py
nkunyim_iam/auth/deprecate.py
nkunyim_iam/auth/common/__init__.py
nkunyim_iam/auth/common/encoding.py
nkunyim_iam/auth/common/errors.py
nkunyim_iam/auth/common/security.py
nkunyim_iam/auth/common/urls.py
nkunyim_iam/auth/integrations/__init__.py
nkunyim_iam/auth/integrations/base_client/__init__.py
nkunyim_iam/auth/integrations/base_client/async_app.py
nkunyim_iam/auth/integrations/base_client/async_openid.py
nkunyim_iam/auth/integrations/base_client/errors.py
nkunyim_iam/auth/integrations/base_client/framework_integration.py
nkunyim_iam/auth/integrations/base_client/registry.py
nkunyim_iam/auth/integrations/base_client/sync_app.py
nkunyim_iam/auth/integrations/base_client/sync_openid.py
nkunyim_iam/auth/integrations/django_client/__init__.py
nkunyim_iam/auth/integrations/django_client/apps.py
nkunyim_iam/auth/integrations/django_client/integration.py
nkunyim_iam/auth/integrations/django_oauth1/__init__.py
nkunyim_iam/auth/integrations/django_oauth1/authorization_server.py
nkunyim_iam/auth/integrations/django_oauth1/nonce.py
nkunyim_iam/auth/integrations/django_oauth1/resource_protector.py
nkunyim_iam/auth/integrations/django_oauth2/__init__.py
nkunyim_iam/auth/integrations/django_oauth2/authorization_server.py
nkunyim_iam/auth/integrations/django_oauth2/endpoints.py
nkunyim_iam/auth/integrations/django_oauth2/requests.py
nkunyim_iam/auth/integrations/django_oauth2/resource_protector.py
nkunyim_iam/auth/integrations/django_oauth2/signals.py
nkunyim_iam/auth/integrations/requests_client/__init__.py
nkunyim_iam/auth/integrations/requests_client/assertion_session.py
nkunyim_iam/auth/integrations/requests_client/oauth1_session.py
nkunyim_iam/auth/integrations/requests_client/oauth2_session.py
nkunyim_iam/auth/integrations/requests_client/utils.py
nkunyim_iam-0.5.4.dist-info/METADATA
nkunyim_iam-0.5.4.dist-info/WHEEL
nkunyim_iam-0.5.4.dist-info/licenses/LICENSE
nkunyim_iam-0.5.4.dist-info/RECORD
