Metadata-Version: 2.4
Name: nkunyim_iam
Version: 0.5.4
Summary: Auth library for Nkunyim apps and services
Project-URL: Homepage, https://github.com/nkunyim/nkunyim_iam
Project-URL: Issues, https://github.com/nkunyim/nkunyim_iam/issues
Author-email: Enoch Enchill <et.enchill@gmail.com>
License-Expression: Apache-2.0
License-File: LICENSE
Classifier: Operating System :: OS Independent
Classifier: Programming Language :: Python :: 3
Requires-Python: >=3.9
